qsvin/__init__.py
qsvin/config.py
qsvin/db_client.py
qsvin/external_api.py
qsvin/qvin.py
qsvin/remote_client.py
qsvin/test.py
qsvin/vin_decoder.py
qsvin-0.0.14.dist-info/METADATA
qsvin-0.0.14.dist-info/WHEEL
qsvin-0.0.14.dist-info/top_level.txt
qsvin-0.0.14.dist-info/RECORD
