Metadata-Version: 2.1
Name: qsvin
Version: 0.0.14
Summary: Package provides functionality for decoding vin data
Home-page: https://github.com/saferide-tech/QuestarVin
Author: Yaroslav Mavliutov
Author-email: yaroslavm@questarauto.com
License: MIT
Keywords: vin
Requires-Dist: databricks-sql-connector
Requires-Dist: requests
Requires-Dist: vininfo
Requires-Dist: openpyxl
